{
  "description": "A drawer is a slide out panel for representing data which may be secondary or not fit on the main screen. Examples are a responsive navigation menu, more details of a selected item on the page. Drawers can be opened from top, bottom, left or right and an overlay covers the screen to focus more attention on the drawer contents.",
  "tags": {},
  "displayName": "NeonDrawer",
  "exportName": "default",
  "props": [
    {
      "name": "open",
      "tags": {},
      "description": "Set the drawer to visible.",
      "type": {
        "name": "boolean"
      },
      "required": true
    },
    {
      "name": "dismissable",
      "tags": {},
      "description": "Whether or not the user is allowed to dismiss the modal by clicking outside of the modal or pressing escape.",
      "type": {
        "name": "boolean"
      },
      "defaultValue": {
        "func": false,
        "value": "true"
      }
    },
    {
      "name": "fullWidth",
      "tags": {},
      "description": "If true, remove the padding applied to the drawer.",
      "type": {
        "name": "boolean"
      },
      "defaultValue": {
        "func": false,
        "value": "false"
      }
    },
    {
      "name": "position",
      "tags": {},
      "description": "The location of the drawer.",
      "type": {
        "name": "NeonPosition"
      },
      "defaultValue": {
        "func": false,
        "value": "NeonPosition.Left"
      }
    },
    {
      "name": "overlay",
      "tags": {},
      "description": "Display a semi-transparent overlay under the drawer, but over the rest of the page.",
      "type": {
        "name": "boolean"
      },
      "defaultValue": {
        "func": false,
        "value": "true"
      }
    }
  ],
  "events": [
    {
      "name": "close",
      "description": "Emitted when the drawer is closed.",
      "type": {
        "names": [
          "void"
        ]
      }
    }
  ],
  "slots": [
    {
      "name": "default",
      "description": "the contents of the drawer"
    }
  ]
}